evmdeploy/__init__.py
evmdeploy/contract.py
evmdeploy/deploy.py
evmdeploy/exceptions.py
evmdeploy/artifacts/__init__.py
evmdeploy/artifacts/model.py
evmdeploy/artifacts/storage.py
evmdeploy/cli/__init__.py
evmdeploy/cli/main.py
evmdeploy/compiler/__init__.py
evmdeploy/compiler/linker.py
evmdeploy/compiler/solidity.py
evmdeploy/crypto/__init__.py
evmdeploy/crypto/signer.py
evmdeploy/deployer/__init__.py
evmdeploy/deployer/deployer.py
evmdeploy/deployer/gas.py
evmdeploy/encoding/__init__.py
evmdeploy/encoding/constructor.py
evmdeploy/network/__init__.py
evmdeploy/network/evm.py
evmdeploy/utils/__init__.py
evmdeploy/utils/hashing.py
evmdeploy/utils/paths.py
evmdeploy-0.1.0.1.dist-info/licenses/LICENSE
evmdeploy-0.1.0.1.dist-info/METADATA
evmdeploy-0.1.0.1.dist-info/WHEEL
evmdeploy-0.1.0.1.dist-info/entry_points.txt
evmdeploy-0.1.0.1.dist-info/top_level.txt
evmdeploy-0.1.0.1.dist-info/RECORD
