Metadata-Version: 2.4
Name: evmdeploy
Version: 0.1.0.1
Summary: Minimal Python library to compile Solidity contracts and deploy them to EVM-compatible chains
Author-email: Rakib Hossain <rakib4ggp@gmail.com>
License-Expression: MIT
Project-URL: Homepage, https://github.com/rakibhossain72/evmdeploy
Project-URL: Repository, https://github.com/rakibhossain72/evmdeploy.git
Project-URL: Issues, https://github.com/rakibhossain72/evmdeploy/issues
Keywords: ethereum,evm,solidity,deployment,web3,blockchain
Classifier: Development Status :: 3 - Alpha
Classifier: Intended Audience :: Developers
Classifier: Topic :: Software Development :: Build Tools
Classifier: Topic :: Software Development :: Compilers
Classifier: Programming Language :: Python :: 3
Classifier: Programming Language :: Python :: 3.10
Classifier: Programming Language :: Python :: 3.11
Classifier: Programming Language :: Python :: 3.12
Classifier: Programming Language :: Python :: 3 :: Only
Classifier: Operating System :: OS Independent
Requires-Python: >=3.10
License-File: LICENSE
Requires-Dist: web3>=7.14.0
Requires-Dist: py-solc-x>=2.0.5
Requires-Dist: eth-abi>=5.2.0
Requires-Dist: eth-utils>=5.3.1
Dynamic: license-file
